setup.py
gaus_bino_distribution/Binomialdistribution.py
gaus_bino_distribution/Gaussiandistribution.py
gaus_bino_distribution/Generaldistribution.py
gaus_bino_distribution/__init__.py
gaus_bino_distribution.egg-info/PKG-INFO
gaus_bino_distribution.egg-info/SOURCES.txt
gaus_bino_distribution.egg-info/dependency_links.txt
gaus_bino_distribution.egg-info/not-zip-safe
gaus_bino_distribution.egg-info/top_level.txt