Metadata-Version: 1.0
Name: gaus-bino-distribution
Version: 1.0
Summary: Gaussian and Binomial distributions
Home-page: UNKNOWN
Author: Navjot Singh Bajaj
Author-email: singhnavjotb246@gmail.com
License: UNKNOWN
Platform: UNKNOWN
